README.md
setup.py
clever/__init__.py
clever/api_client.py
clever/configuration.py
clever/importer.py
clever/rest.py
clever/version.py
clever.egg-info/PKG-INFO
clever.egg-info/SOURCES.txt
clever.egg-info/dependency_links.txt
clever.egg-info/requires.txt
clever.egg-info/top_level.txt
clever/apis/__init__.py
clever/apis/data_api.py
clever/apis/events_api.py
clever/models/__init__.py
clever/models/bad_request.py
clever/models/contact.py
clever/models/contact_object.py
clever/models/contact_response.py
clever/models/contacts_created.py
clever/models/contacts_deleted.py
clever/models/contacts_response.py
clever/models/contacts_updated.py
clever/models/course.py
clever/models/course_object.py
clever/models/course_response.py
clever/models/courses_created.py
clever/models/courses_deleted.py
clever/models/courses_response.py
clever/models/courses_updated.py
clever/models/credentials.py
clever/models/district.py
clever/models/district_admin.py
clever/models/district_admin_object.py
clever/models/district_admin_response.py
clever/models/district_admins_response.py
clever/models/district_object.py
clever/models/district_response.py
clever/models/districtadmins_created.py
clever/models/districtadmins_deleted.py
clever/models/districtadmins_updated.py
clever/models/districts_created.py
clever/models/districts_deleted.py
clever/models/districts_response.py
clever/models/districts_updated.py
clever/models/event.py
clever/models/event_response.py
clever/models/events_response.py
clever/models/internal_error.py
clever/models/location.py
clever/models/name.py
clever/models/not_found.py
clever/models/principal.py
clever/models/school.py
clever/models/school_admin.py
clever/models/school_admin_object.py
clever/models/school_admin_response.py
clever/models/school_admins_response.py
clever/models/school_object.py
clever/models/school_response.py
clever/models/schooladmins_created.py
clever/models/schooladmins_deleted.py
clever/models/schooladmins_updated.py
clever/models/schools_created.py
clever/models/schools_deleted.py
clever/models/schools_response.py
clever/models/schools_updated.py
clever/models/section.py
