Metadata-Version: 1.0
Name: clever
Version: 3.0.1
Summary: Clever API
Home-page: UNKNOWN
Author: UNKNOWN
Author-email: UNKNOWN
License: UNKNOWN
Keywords: Swagger,Clever API
Platform: UNKNOWN
